torlib/__init__.py
torlib/crawler/__init__.py
torlib/crawler/github_crawler.py
torlib-0.0.4.dist-info/LICENSE
torlib-0.0.4.dist-info/METADATA
torlib-0.0.4.dist-info/WHEEL
torlib-0.0.4.dist-info/top_level.txt
torlib-0.0.4.dist-info/RECORD
