Metadata-Version: 2.1
Name: torlib
Version: 0.0.4
Summary: A utility package that can help in many scenarios :D
Home-page: https://noppadol-assava.github.io/torlib
Author: Noppadol Assavakamhaenghan
Author-email: noppadol.assava@gmail.com
Project-URL: Bug Tracker, https://github.com/noppadol-assava/torlib/issues
Project-URL: Documentation, https://noppadol-assava.github.io/torlib/docs
Project-URL: Source Code, https://github.com/noppadol-assava/torlib
Classifier: Programming Language :: Python :: 3
Classifier: License :: OSI Approved :: MIT License
Classifier: Operating System :: OS Independent
Requires-Python: >=3.6
License-File: LICENSE
Requires-Dist: tqdm
Requires-Dist: responses
